{
  "id": "1700053357086-724b",
  "lang": "en",
  "context_name": "weather_forecast",
  "skill_name": "weather_forecast_skill",
  "action_name": "get_forecast",
  "skill_config": {
    "name": "Weather Forecast",
    "bridge": "nodejs",
    "version": "1.0.0",
    "workflow": []
  },
  "skill_config_path": "skills/native/weather_forecast_skill/skill.json",
  "utterance": "Is github.com down?",
  "entities": [],
  "action_arguments": {
    "location": "Shanghai"
  },
  "sentiment": {
    "vote": "neutral",
    "score": 0
  },
  "context": {
    "utterances": ["What is the weather in Shanghai?"],
    "action_arguments": [{ "location": "Shanghai" }],
    "entities": [],
    "sentiments": [{ "vote": "neutral", "score": 0 }],
    "data": {}
  },
  "extra_context": {
    "lang": "en",
    "date": "2023-11-15",
    "time": "21:02:37",
    "timestamp": 1700053357000,
    "date_time": "2023-11-15T21:02:37+08:00",
    "week_day": "Wednesday"
  },
  "output": {
    "codes": "",
    "answer": "Here is the forecast.",
    "core": {}
  }
}
